odoo/addons/partner_second_lastname/README.rst
odoo/addons/partner_second_lastname/__init__.py
odoo/addons/partner_second_lastname/__manifest__.py
odoo/addons/partner_second_lastname/i18n/am.po
odoo/addons/partner_second_lastname/i18n/ar.po
odoo/addons/partner_second_lastname/i18n/bg.po
odoo/addons/partner_second_lastname/i18n/bs.po
odoo/addons/partner_second_lastname/i18n/ca.po
odoo/addons/partner_second_lastname/i18n/cs.po
odoo/addons/partner_second_lastname/i18n/da.po
odoo/addons/partner_second_lastname/i18n/de.po
odoo/addons/partner_second_lastname/i18n/el_GR.po
odoo/addons/partner_second_lastname/i18n/en_GB.po
odoo/addons/partner_second_lastname/i18n/es.po
odoo/addons/partner_second_lastname/i18n/es_CR.po
odoo/addons/partner_second_lastname/i18n/es_EC.po
odoo/addons/partner_second_lastname/i18n/es_MX.po
odoo/addons/partner_second_lastname/i18n/es_VE.po
odoo/addons/partner_second_lastname/i18n/et.po
odoo/addons/partner_second_lastname/i18n/eu.po
odoo/addons/partner_second_lastname/i18n/fi.po
odoo/addons/partner_second_lastname/i18n/fr.po
odoo/addons/partner_second_lastname/i18n/fr_CA.po
odoo/addons/partner_second_lastname/i18n/fr_CH.po
odoo/addons/partner_second_lastname/i18n/gl.po
odoo/addons/partner_second_lastname/i18n/hr.po
odoo/addons/partner_second_lastname/i18n/hr_HR.po
odoo/addons/partner_second_lastname/i18n/hu.po
odoo/addons/partner_second_lastname/i18n/it.po
odoo/addons/partner_second_lastname/i18n/ja.po
odoo/addons/partner_second_lastname/i18n/lt.po
odoo/addons/partner_second_lastname/i18n/lv.po
odoo/addons/partner_second_lastname/i18n/mk.po
odoo/addons/partner_second_lastname/i18n/mn.po
odoo/addons/partner_second_lastname/i18n/nb.po
odoo/addons/partner_second_lastname/i18n/nb_NO.po
odoo/addons/partner_second_lastname/i18n/nl.po
odoo/addons/partner_second_lastname/i18n/nl_BE.po
odoo/addons/partner_second_lastname/i18n/nl_NL.po
odoo/addons/partner_second_lastname/i18n/partner_second_lastname.pot
odoo/addons/partner_second_lastname/i18n/pl.po
odoo13_addon_partner_second_lastname-13.0.2.0.0.dist-info/METADATA
odoo13_addon_partner_second_lastname-13.0.2.0.0.dist-info/WHEEL
odoo13_addon_partner_second_lastname-13.0.2.0.0.dist-info/top_level.txt
odoo13_addon_partner_second_lastname-13.0.2.0.0.dist-info/RECORD
